{
  "symbol": "ARTIS",
  "name": "Artis Turba",
  "type": "ERC20",
  "address": "0x082E13494f12EBB7206FBf67E22A6E1975A1A669",
  "ens_address": "",
  "decimals": 8,
  "website": "https://www.artisturba.com/",
  "logo": { "src": "", "width": "", "height": "", "ipfs_hash": "" },
  "support": { "email": "", "url": "" },
  "social": {
    "blog": "",
    "chat": "",
    "discord": "",
    "facebook": "",
    "forum": "",
    "github": "",
    "gitter": "",
    "instagram": "",
    "linkedin": "",
    "reddit": "",
    "slack": "",
    "telegram": "",
    "twitter": "",
    "youtube": ""
  }
}
