{
  "symbol": "PARTY",
  "name": "MONEY PARTY",
  "type": "ERC20",
  "address": "0x314bD765cAB4774b2E547eB0aA15013e03FF74d2",
  "ens_address": "",
  "decimals": 6,
  "website": "https://moneyparty.vip/",
  "logo": { "src": "", "width": "", "height": "", "ipfs_hash": "" },
  "support": { "email": "", "url": "" },
  "social": {
    "blog": "",
    "chat": "",
    "discord": "",
    "facebook": "",
    "forum": "",
    "github": "",
    "gitter": "",
    "instagram": "",
    "linkedin": "",
    "reddit": "",
    "slack": "",
    "telegram": "",
    "twitter": "",
    "youtube": ""
  }
}
