{
  "symbol": "TMUS.CX",
  "name": "T-Mobile US Inc",
  "type": "ERC20",
  "address": "0x4D9F37E79723A3bb910E1b2fc7b1ef851261B1d9",
  "ens_address": "",
  "decimals": 8,
  "website": "https://currency.com/",
  "logo": { "src": "", "width": "", "height": "", "ipfs_hash": "" },
  "support": { "email": "", "url": "" },
  "social": {
    "blog": "",
    "chat": "",
    "discord": "",
    "facebook": "",
    "forum": "",
    "github": "",
    "gitter": "",
    "instagram": "",
    "linkedin": "",
    "reddit": "",
    "slack": "",
    "telegram": "",
    "twitter": "",
    "youtube": ""
  }
}
