{
  "symbol": "VPP",
  "name": "Virtue Poker Points",
  "type": "ERC20",
  "address": "0x5EeAA2DCb23056F4E8654a349E57eBE5e76b5e6e",
  "ens_address": "",
  "decimals": 18,
  "website": "",
  "logo": { "src": "", "width": "", "height": "", "ipfs_hash": "" },
  "support": { "email": "", "url": "" },
  "social": {
    "blog": "",
    "chat": "",
    "discord": "",
    "facebook": "",
    "forum": "",
    "github": "",
    "gitter": "",
    "instagram": "",
    "linkedin": "",
    "reddit": "",
    "slack": "",
    "telegram": "",
    "twitter": "",
    "youtube": ""
  }
}
