{
  "symbol": "PCT",
  "name": "PerksCoin",
  "type": "ERC20",
  "address": "0x5ebE6a342a93102393EdD9D2e458C689e5aC0bb3",
  "ens_address": "",
  "decimals": 8,
  "website": "https://cannasos.com/crowdsale-ico",
  "logo": { "src": "", "width": "", "height": "", "ipfs_hash": "" },
  "support": { "email": "", "url": "" },
  "social": {
    "blog": "",
    "chat": "",
    "discord": "",
    "facebook": "",
    "forum": "",
    "github": "",
    "gitter": "",
    "instagram": "",
    "linkedin": "",
    "reddit": "",
    "slack": "",
    "telegram": "",
    "twitter": "",
    "youtube": ""
  }
}
