{
  "symbol": "XQC",
  "name": "Quras Token",
  "type": "ERC20",
  "address": "0x70da48f4B7e83c386ef983D4CEF4e58c2c09D8Ac",
  "ens_address": "",
  "decimals": 8,
  "website": "https://quras.io/",
  "logo": { "src": "", "width": "", "height": "", "ipfs_hash": "" },
  "support": { "email": "", "url": "" },
  "social": {
    "blog": "",
    "chat": "",
    "discord": "",
    "facebook": "",
    "forum": "",
    "github": "",
    "gitter": "",
    "instagram": "",
    "linkedin": "",
    "reddit": "",
    "slack": "",
    "telegram": "",
    "twitter": "",
    "youtube": ""
  }
}
