{
  "symbol": "WRK",
  "name": "WorkCoin",
  "type": "ERC20",
  "address": "0x71e8d74ff1c923e369d0e70dfb09866629c4dd35",
  "ens_address": "",
  "decimals": 18,
  "website": "https://workcoin.net/",
  "logo": {
    "src": "https://workcoin.net/images/workcoin_logo.svg",
    "width": "",
    "height": "",
    "ipfs_hash": ""
  },
  "support": { "email": "support@workcoin.net", "url": "" },
  "social": {
    "blog": "https://medium.com/workcoin",
    "chat": "",
    "facebook": "https://www.facebook.com/workcoingroup/",
    "forum": "",
    "github": "https://github.com/TMWorkCoin",
    "gitter": "",
    "instagram": "",
    "linkedin": "",
    "reddit": "",
    "slack": "",
    "telegram": "http://t.me/workcoin",
    "twitter": "https://twitter.com/realWorkCoin",
    "youtube": ""
  }
}
