{
  "symbol": "HUG",
  "name": "Hubbsgold",
  "type": "ERC20",
  "address": "0x79D617768C70936F097Cf6E82d1FDCa15dC4417C",
  "ens_address": "",
  "decimals": 8,
  "website": "https://myhubb.online/",
  "logo": { "src": "", "width": "", "height": "", "ipfs_hash": "" },
  "support": { "email": "", "url": "" },
  "social": {
    "blog": "",
    "chat": "",
    "discord": "",
    "facebook": "",
    "forum": "",
    "github": "",
    "gitter": "",
    "instagram": "",
    "linkedin": "",
    "reddit": "",
    "slack": "",
    "telegram": "",
    "twitter": "",
    "youtube": ""
  }
}
