{
  "symbol": "DOGEBULL",
  "name": "3X Long Dogecoin Token",
  "type": "ERC20",
  "address": "0x7AA6b33fB7F395DDBca7b7A33264A3c799Fa626f",
  "ens_address": "",
  "decimals": 18,
  "website": "https://ftx.com/tokens/DOGEBULL",
  "logo": { "src": "", "width": "", "height": "", "ipfs_hash": "" },
  "support": { "email": "", "url": "" },
  "social": {
    "blog": "",
    "chat": "",
    "discord": "",
    "facebook": "",
    "forum": "",
    "github": "",
    "gitter": "",
    "instagram": "",
    "linkedin": "",
    "reddit": "",
    "slack": "",
    "telegram": "",
    "twitter": "",
    "youtube": ""
  }
}
