{
  "symbol": "ZERA",
  "name": "ZERACOIN",
  "type": "ERC20",
  "address": "0x8188e51bc678f0070531f0e782718df0027452de",
  "ens_address": "",
  "decimals": 8,
  "website": "http://zeraco.in",
  "logo": {
    "src": "https://res.cloudinary.com/cloudimgstorage/image/upload/v1555411190/ZERA-LOGO-256X256.png",
    "width": "256px",
    "height": "256px",
    "ipfs_hash": ""
  },
  "support": { "email": "support@zeraco.in", "url": "http://zeraco.in" },
  "social": {
    "blog": "",
    "chat": "",
    "facebook": "https://www.facebook.com/Zeraco-581982708994569",
    "forum": "",
    "github": "https://github.com/zinvest",
    "gitter": "",
    "instagram": "",
    "linkedin": "https://www.linkedin.com/in/zinvest-invest-89bb93183",
    "reddit": "",
    "slack": "",
    "telegram": "t.me/zeraco",
    "twitter": "https://twitter.com/zeraco3",
    "youtube": ""
  }
}
