{
  "symbol": "0XESV",
  "name": "0xETH SV",
  "type": "ERC20",
  "address": "0x8E9c3D1F30904E91764B7b8bBFDa3a429b886874",
  "ens_address": "",
  "decimals": 8,
  "website": "https://0xethsv.0xethereumtoken.com/",
  "logo": { "src": "", "width": "", "height": "", "ipfs_hash": "" },
  "support": { "email": "", "url": "" },
  "social": {
    "blog": "",
    "chat": "",
    "discord": "",
    "facebook": "",
    "forum": "",
    "github": "",
    "gitter": "",
    "instagram": "",
    "linkedin": "",
    "reddit": "",
    "slack": "",
    "telegram": "",
    "twitter": "",
    "youtube": ""
  }
}
