{
  "symbol": "QUID",
  "name": "Quid Ika",
  "type": "ERC20",
  "address": "0x9d38F670D15C14716BE1F109a4F453E966A2B6D4",
  "ens_address": "",
  "decimals": 9,
  "website": "",
  "logo": { "src": "", "width": "", "height": "", "ipfs_hash": "" },
  "support": { "email": "", "url": "" },
  "social": {
    "blog": "",
    "chat": "",
    "discord": "",
    "facebook": "",
    "forum": "",
    "github": "",
    "gitter": "",
    "instagram": "",
    "linkedin": "",
    "reddit": "",
    "slack": "",
    "telegram": "",
    "twitter": "",
    "youtube": ""
  }
}
