{
  "symbol": "EGX",
  "name": "Enegra",
  "type": "ERC20",
  "address": "0xa19bbEf64eFF0D060a653e4DF10a57B6d8006d3E",
  "ens_address": "enegraltd.eth",
  "decimals": 18,
  "website": "https://www.enegra.com",
  "logo": {
    "src": "https://ipfs.robotinfra.com/ipfs/QmcZkiYHd2vguXwZ1WqXjTdz3CnJ3MMiKiZY4NXi46tAEQ",
    "width": "512px",
    "height": "512px",
    "ipfs_hash": "QmcZkiYHd2vguXwZ1WqXjTdz3CnJ3MMiKiZY4NXi46tAEQ"
  },
  "support": { "email": "support@enegra.com", "url": "" },
  "social": {
    "blog": "",
    "chat": "",
    "discord": "",
    "facebook": "https://www.facebook.com/enegraltd/",
    "forum": "",
    "github": "",
    "gitter": "",
    "instagram": "https://www.instagram.com/enegraltd/",
    "linkedin": "https://www.linkedin.com/company/enegraltd/about/",
    "reddit": "",
    "slack": "",
    "telegram": "https://t.me/EnegraLtd",
    "twitter": "https://twitter.com/enegraltd",
    "youtube": ""
  }
}
