{
  "symbol": "AER",
  "name": "Aeryus",
  "type": "ERC20",
  "address": "0xac4D22e40bf0B8eF4750a99ED4E935B99A42685E",
  "ens_address": "",
  "decimals": 18,
  "website": "https://aeryus.com/",
  "logo": { "src": "", "width": "", "height": "", "ipfs_hash": "" },
  "support": { "email": "", "url": "" },
  "social": {
    "blog": "",
    "chat": "",
    "discord": "",
    "facebook": "",
    "forum": "",
    "github": "",
    "gitter": "",
    "instagram": "",
    "linkedin": "",
    "reddit": "",
    "slack": "",
    "telegram": "",
    "twitter": "",
    "youtube": ""
  }
}
