{
  "symbol": "COW",
  "name": "Coweye",
  "type": "ERC20",
  "address": "0xC3d6dda603FC15Fd4Bf9303150fe11c7cd6059dc",
  "ens_address": "",
  "decimals": 18,
  "website": "http://coweye.io/",
  "logo": { "src": "", "width": "", "height": "", "ipfs_hash": "" },
  "support": { "email": "", "url": "" },
  "social": {
    "blog": "",
    "chat": "",
    "discord": "",
    "facebook": "",
    "forum": "",
    "github": "",
    "gitter": "",
    "instagram": "",
    "linkedin": "",
    "reddit": "",
    "slack": "",
    "telegram": "",
    "twitter": "",
    "youtube": ""
  }
}
