{
  "symbol": "GALA",
  "name": "GALA",
  "type": "ERC20",
  "address": "0xd1d2Eb1B1e90B638588728b4130137D262C87cae",
  "ens_address": "",
  "decimals": 8,
  "website": "",
  "logo": { "src": "", "width": "", "height": "", "ipfs_hash": "" },
  "support": { "email": "", "url": "" },
  "social": {
    "blog": "",
    "chat": "",
    "discord": "",
    "facebook": "",
    "forum": "",
    "github": "",
    "gitter": "",
    "instagram": "",
    "linkedin": "",
    "reddit": "",
    "slack": "",
    "telegram": "",
    "twitter": "",
    "youtube": ""
  }
}
