{
  "symbol": "LUXO",
  "name": "Luxo",
  "type": "ERC20",
  "address": "0xD39a2CeCBA2657e125Ba6a5c98ad2F6b6D7E83FD",
  "ens_address": "",
  "decimals": 18,
  "website": "",
  "logo": { "src": "", "width": "", "height": "", "ipfs_hash": "" },
  "support": { "email": "", "url": "" },
  "social": {
    "blog": "",
    "chat": "",
    "discord": "",
    "facebook": "",
    "forum": "",
    "github": "",
    "gitter": "",
    "instagram": "",
    "linkedin": "",
    "reddit": "",
    "slack": "",
    "telegram": "",
    "twitter": "",
    "youtube": ""
  }
}
