{
  "symbol": "FLINT",
  "name": "MintFlint",
  "type": "ERC20",
  "address": "0xdad59fd8b366a5536c014da9eb81d19ec9953920",
  "ens_address": "mintflint.eth",
  "decimals": 18,
  "website": "https://mintflint.com",
  "logo": { "src": "", "width": "", "height": "", "ipfs_hash": "" },
  "support": {
    "email": "sam@mintflint.com",
    "url": "https://mintflint.me/trader/support"
  },
  "social": {
    "blog": "",
    "chat": "",
    "facebook": "",
    "forum": "",
    "github": "https://github.com/mintflint",
    "gitter": "",
    "instagram": "",
    "linkedin": "",
    "reddit": "",
    "slack": "",
    "telegram": "t.me/mintflint",
    "twitter": "twitter.com/mintflintapp",
    "youtube": ""
  }
}
