{
  "symbol": "KUE",
  "name": "Kuende Token",
  "type": "ERC20",
  "address": "0xdf1338FbAfe7aF1789151627B886781ba556eF9a",
  "ens_address": "",
  "decimals": 18,
  "website": "https://ico.kuende.com",
  "logo": {
    "src": "https://cdn.kuende.com/images/new-klogo.png",
    "width": "150",
    "height": "150",
    "ipfs_hash": ""
  },
  "support": { "email": "token@kuende.com", "url": "" },
  "social": {
    "blog": "https://medium.com/kuende",
    "chat": "",
    "facebook": "https://www.facebook.com/kuende.world",
    "forum": "",
    "github": "",
    "gitter": "",
    "instagram": "https://www.instagram.com/kuende_com/",
    "linkedin": "https://www.linkedin.com/company/kuende/",
    "reddit": "https://reddit.com/r/kuende/",
    "slack": "",
    "telegram": "https://t.me/kuende",
    "twitter": "https://twitter.com/kuende_com",
    "youtube": "https://www.youtube.com/c/KuendecomOfficial"
  }
}
