{
  "symbol": "CTAT",
  "name": "Cryptassist",
  "type": "ERC20",
  "address": "0xF7461C8D8E469e9c41a9013dC09Ba8AbED66ef65",
  "ens_address": "",
  "decimals": 8,
  "website": "https://www.cryptassist.io/en",
  "logo": { "src": "", "width": "", "height": "", "ipfs_hash": "" },
  "support": { "email": "", "url": "" },
  "social": {
    "blog": "",
    "chat": "",
    "discord": "",
    "facebook": "",
    "forum": "",
    "github": "",
    "gitter": "",
    "instagram": "",
    "linkedin": "",
    "reddit": "",
    "slack": "",
    "telegram": "",
    "twitter": "",
    "youtube": ""
  }
}
