{
  "symbol": "MGA",
  "name": "Metagame Arena",
  "type": "ERC20",
  "address": "0x03aC6AB6A9a91a0fcdec7D85b38bDFBb719ec02f",
  "ens_address": "",
  "decimals": 18,
  "website": "",
  "logo": { "src": "", "width": "", "height": "", "ipfs_hash": "" },
  "support": { "email": "", "url": "" },
  "social": {
    "blog": "",
    "chat": "",
    "discord": "",
    "facebook": "",
    "forum": "",
    "github": "",
    "gitter": "",
    "instagram": "",
    "linkedin": "",
    "reddit": "",
    "slack": "",
    "telegram": "",
    "twitter": "",
    "youtube": ""
  }
}
