{
  "symbol": "CHECK",
  "name": "Paycheck",
  "type": "ERC20",
  "address": "0x0F17771cCF1B990DbE2a6D7f61183C9b29997e36",
  "ens_address": "",
  "decimals": 6,
  "website": "",
  "logo": { "src": "", "width": "", "height": "", "ipfs_hash": "" },
  "support": { "email": "", "url": "" },
  "social": {
    "blog": "",
    "chat": "",
    "discord": "",
    "facebook": "",
    "forum": "",
    "github": "",
    "gitter": "",
    "instagram": "",
    "linkedin": "",
    "reddit": "",
    "slack": "",
    "telegram": "",
    "twitter": "",
    "youtube": ""
  }
}
