{
  "symbol": "AXLUSDC",
  "name": "Axelar USDC",
  "type": "ERC20",
  "address": "0x4268B8F0B87b6Eae5d897996E6b845ddbD99Adf3",
  "ens_address": "",
  "decimals": 6,
  "website": "",
  "logo": { "src": "", "width": "", "height": "", "ipfs_hash": "" },
  "support": { "email": "", "url": "" },
  "social": {
    "blog": "",
    "chat": "",
    "discord": "",
    "facebook": "",
    "forum": "",
    "github": "",
    "gitter": "",
    "instagram": "",
    "linkedin": "",
    "reddit": "",
    "slack": "",
    "telegram": "",
    "twitter": "",
    "youtube": ""
  }
}
