{
  "symbol": "TC",
  "name": "TTcoin",
  "type": "ERC20",
  "address": "0x659049786cB66E4486b8C0E0cCC90a5929a21162",
  "ens_address": "",
  "decimals": 4,
  "website": "",
  "logo": { "src": "", "width": "", "height": "", "ipfs_hash": "" },
  "support": { "email": "", "url": "" },
  "social": {
    "blog": "",
    "chat": "",
    "discord": "",
    "facebook": "",
    "forum": "",
    "github": "",
    "gitter": "",
    "instagram": "",
    "linkedin": "",
    "reddit": "",
    "slack": "",
    "telegram": "",
    "twitter": "",
    "youtube": ""
  }
}
