{
  "symbol": "AOT",
  "name": "Age Of Tanks",
  "type": "ERC20",
  "address": "0x9589014F7a8547B89A6331eEEe32b7fBd5852af9",
  "ens_address": "",
  "decimals": 6,
  "website": "",
  "logo": { "src": "", "width": "", "height": "", "ipfs_hash": "" },
  "support": { "email": "", "url": "" },
  "social": {
    "blog": "",
    "chat": "",
    "discord": "",
    "facebook": "",
    "forum": "",
    "github": "",
    "gitter": "",
    "instagram": "",
    "linkedin": "",
    "reddit": "",
    "slack": "",
    "telegram": "",
    "twitter": "",
    "youtube": ""
  }
}
