{
  "symbol": "ADMC",
  "name": "Adamant Coin",
  "type": "ERC20",
  "address": "0xA55EF2fB2B7b6A60371FD3def9B806E74a48bE69",
  "ens_address": "",
  "decimals": 9,
  "website": "",
  "logo": { "src": "", "width": "", "height": "", "ipfs_hash": "" },
  "support": { "email": "", "url": "" },
  "social": {
    "blog": "",
    "chat": "",
    "discord": "",
    "facebook": "",
    "forum": "",
    "github": "",
    "gitter": "",
    "instagram": "",
    "linkedin": "",
    "reddit": "",
    "slack": "",
    "telegram": "",
    "twitter": "",
    "youtube": ""
  }
}
