{
  "symbol": "BMCC",
  "name": "Binance Multi Chain Capital",
  "type": "ERC20",
  "address": "0xb6D8EE99D5d6cfe7D80b666e6fF5e74e3f72756b",
  "ens_address": "",
  "decimals": 9,
  "website": "",
  "logo": { "src": "", "width": "", "height": "", "ipfs_hash": "" },
  "support": { "email": "", "url": "" },
  "social": {
    "blog": "",
    "chat": "",
    "discord": "",
    "facebook": "",
    "forum": "",
    "github": "",
    "gitter": "",
    "instagram": "",
    "linkedin": "",
    "reddit": "",
    "slack": "",
    "telegram": "",
    "twitter": "",
    "youtube": ""
  }
}
