{
  "symbol": "ELONBANK",
  "name": "ElonBank",
  "type": "ERC20",
  "address": "0xD5f363F83b36E10e8a823166b992c0bDc3deDE2C",
  "ens_address": "",
  "decimals": 5,
  "website": "",
  "logo": { "src": "", "width": "", "height": "", "ipfs_hash": "" },
  "support": { "email": "", "url": "" },
  "social": {
    "blog": "",
    "chat": "",
    "discord": "",
    "facebook": "",
    "forum": "",
    "github": "",
    "gitter": "",
    "instagram": "",
    "linkedin": "",
    "reddit": "",
    "slack": "",
    "telegram": "",
    "twitter": "",
    "youtube": ""
  }
}
