{
  "symbol": "ASH",
  "name": "Ash Token",
  "type": "ERC20",
  "address": "0xE3c1bDeEc4dB91CD90c336776332FAe2E00fdDd9",
  "ens_address": "",
  "decimals": 9,
  "website": "",
  "logo": { "src": "", "width": "", "height": "", "ipfs_hash": "" },
  "support": { "email": "", "url": "" },
  "social": {
    "blog": "",
    "chat": "",
    "discord": "",
    "facebook": "",
    "forum": "",
    "github": "",
    "gitter": "",
    "instagram": "",
    "linkedin": "",
    "reddit": "",
    "slack": "",
    "telegram": "",
    "twitter": "",
    "youtube": ""
  }
}
