{
  "symbol": "TORJ",
  "name": "TORJ.world",
  "type": "BEP20",
  "address": "0xECD2376a8C5Ece76323282441a1b935Bbcb45Ec2",
  "ens_address": "",
  "decimals": 3,
  "website": "",
  "logo": { "src": "", "width": "", "height": "", "ipfs_hash": "" },
  "support": { "email": "", "url": "" },
  "social": {
    "blog": "",
    "chat": "",
    "discord": "",
    "facebook": "",
    "forum": "",
    "github": "",
    "gitter": "",
    "instagram": "",
    "linkedin": "",
    "reddit": "",
    "slack": "",
    "telegram": "",
    "twitter": "",
    "youtube": ""
  }
}
