{
  "symbol": "KUJI",
  "name": "Kujira",
  "type": "ERC20",
  "address": "0x3A18dcC9745eDcD1Ef33ecB93b0b6eBA5671e7Ca",
  "ens_address": "",
  "decimals": 6,
  "website": "",
  "logo": { "src": "", "width": "", "height": "", "ipfs_hash": "" },
  "support": { "email": "", "url": "" },
  "social": {
    "blog": "",
    "chat": "",
    "discord": "",
    "facebook": "",
    "forum": "",
    "github": "",
    "gitter": "",
    "instagram": "",
    "linkedin": "",
    "reddit": "",
    "slack": "",
    "telegram": "",
    "twitter": "",
    "youtube": ""
  }
}
