{
  "symbol": "AXL-WSTETH",
  "name": "Bridged Wrapped stETH  Axelar ",
  "type": "ERC20",
  "address": "0x9cfB13E6c11054ac9fcB92BA89644F30775436e4",
  "ens_address": "",
  "decimals": 18,
  "website": "",
  "logo": { "src": "", "width": "", "height": "", "ipfs_hash": "" },
  "support": { "email": "", "url": "" },
  "social": {
    "blog": "",
    "chat": "",
    "discord": "",
    "facebook": "",
    "forum": "",
    "github": "",
    "gitter": "",
    "instagram": "",
    "linkedin": "",
    "reddit": "",
    "slack": "",
    "telegram": "",
    "twitter": "",
    "youtube": ""
  }
}
