{
  "symbol": "FQXT",
  "name": "Flyquex Test",
  "type": "ERC20",
  "address": "0x5D47033e140f7b589CC2545416eC9D7a712A7de9",
  "ens_address": "",
  "decimals": 8,
  "website": "",
  "logo": { "src": "", "width": "", "height": "", "ipfs_hash": "" },
  "support": { "email": "aaryanrahi@bskuare.com", "url": "" },
  "social": {
    "blog": "",
    "chat": "",
    "discord": "",
    "facebook": "",
    "forum": "",
    "github": "",
    "gitter": "",
    "instagram": "",
    "linkedin": "",
    "reddit": "",
    "slack": "",
    "telegram": "",
    "twitter": "",
    "youtube": ""
  }
}
