{
  "symbol": "SUKU",
  "name": "SUKU",
  "type": "ERC20",
  "address": "0x60Ea918FC64360269Da4efBDA11d8fC6514617C6",
  "ens_address": "",
  "decimals": 18,
  "website": "",
  "logo": { "src": "", "width": "", "height": "", "ipfs_hash": "" },
  "support": { "email": "", "url": "" },
  "social": {
    "blog": "",
    "chat": "",
    "discord": "",
    "facebook": "",
    "forum": "",
    "github": "",
    "gitter": "",
    "instagram": "",
    "linkedin": "",
    "reddit": "",
    "slack": "",
    "telegram": "",
    "twitter": "",
    "youtube": ""
  }
}
