{
  "symbol": "SUSHI",
  "name": "SushiToken (PoS)",
  "type": "ERC20",
  "address": "0x0b3F868E0BE5597D5DB7fEB59E1CADBb0fdDa50a",
  "ens_address": "",
  "decimals": 18,
  "website": "",
  "logo": { "src": "", "width": "", "height": "", "ipfs_hash": "" },
  "support": { "email": "", "url": "" },
  "social": {
    "blog": "",
    "chat": "",
    "discord": "",
    "facebook": "",
    "forum": "",
    "github": "",
    "gitter": "",
    "instagram": "",
    "linkedin": "",
    "reddit": "",
    "slack": "",
    "telegram": "",
    "twitter": "",
    "youtube": ""
  }
}
