{
  "symbol": "TRYB",
  "name": "BiLira",
  "type": "ERC20",
  "address": "0x4Fb71290Ac171E1d144F7221D882BECAc7196EB5",
  "ens_address": "",
  "decimals": 6,
  "website": "",
  "logo": { "src": "", "width": "", "height": "", "ipfs_hash": "" },
  "support": { "email": "", "url": "" },
  "social": {
    "blog": "",
    "chat": "",
    "discord": "",
    "facebook": "",
    "forum": "",
    "github": "",
    "gitter": "",
    "instagram": "",
    "linkedin": "",
    "reddit": "",
    "slack": "",
    "telegram": "",
    "twitter": "",
    "youtube": ""
  }
}
