{
  "symbol": "AWK",
  "name": "Awkward Monkey",
  "type": "ERC20",
  "address": "0x16CEC756a0FcbA1d7ce95dF5A46406c469a9128a",
  "ens_address": "",
  "decimals": 18,
  "website": "",
  "logo": {
    "src": "https://assets.coingecko.com/coins/images/38623/thumb/AWK-BASE-Profile-Logo-based1.png?1718161968",
    "width": "",
    "height": "",
    "ipfs_hash": ""
  },
  "support": { "email": "", "url": "" },
  "social": {
    "blog": "",
    "chat": "",
    "discord": "",
    "facebook": "",
    "forum": "",
    "github": "",
    "gitter": "",
    "instagram": "",
    "linkedin": "",
    "reddit": "",
    "slack": "",
    "telegram": "",
    "twitter": "",
    "youtube": ""
  }
}
