{
  "symbol": "DOOK",
  "name": "Dook",
  "type": "ERC20",
  "address": "0x461eE40928677644b8195662Ab91BcdaAE6Ef105",
  "ens_address": "",
  "decimals": 18,
  "website": "",
  "logo": {
    "src": "https://assets.coingecko.com/coins/images/38594/thumb/P3oYXNbf_400x400.jpeg?1718927359",
    "width": "",
    "height": "",
    "ipfs_hash": ""
  },
  "support": { "email": "", "url": "" },
  "social": {
    "blog": "",
    "chat": "",
    "discord": "",
    "facebook": "",
    "forum": "",
    "github": "",
    "gitter": "",
    "instagram": "",
    "linkedin": "",
    "reddit": "",
    "slack": "",
    "telegram": "",
    "twitter": "",
    "youtube": ""
  }
}
