{
  "symbol": "DYL",
  "name": "Dyl",
  "type": "ERC20",
  "address": "0x4A506181f07Da5ddFDA4ca4c2Fa4c67001dB94B4",
  "ens_address": "",
  "decimals": 18,
  "website": "",
  "logo": {
    "src": "https://assets.coingecko.com/coins/images/32550/thumb/Dyl-pfp-200x.png?1698479973",
    "width": "",
    "height": "",
    "ipfs_hash": ""
  },
  "support": { "email": "", "url": "" },
  "social": {
    "blog": "",
    "chat": "",
    "discord": "",
    "facebook": "",
    "forum": "",
    "github": "",
    "gitter": "",
    "instagram": "",
    "linkedin": "",
    "reddit": "",
    "slack": "",
    "telegram": "",
    "twitter": "",
    "youtube": ""
  }
}
