{
  "symbol": "EVERY",
  "name": "Everyworld",
  "type": "ERC20",
  "address": "0x717d31A60a9e811469673429c9F8Ea24358990f1",
  "ens_address": "",
  "decimals": 18,
  "website": "",
  "logo": {
    "src": "https://assets.coingecko.com/coins/images/36799/thumb/coin_gecko.png?1714459237",
    "width": "",
    "height": "",
    "ipfs_hash": ""
  },
  "support": { "email": "", "url": "" },
  "social": {
    "blog": "",
    "chat": "",
    "discord": "",
    "facebook": "",
    "forum": "",
    "github": "",
    "gitter": "",
    "instagram": "",
    "linkedin": "",
    "reddit": "",
    "slack": "",
    "telegram": "",
    "twitter": "",
    "youtube": ""
  }
}
