{
  "symbol": "BOLT",
  "name": "BOLT on Base",
  "type": "ERC20",
  "address": "0x7Cf7132EdE0ca592A236b6198A681bB7B42dd5ae",
  "ens_address": "",
  "decimals": 18,
  "website": "",
  "logo": {
    "src": "https://assets.coingecko.com/coins/images/38449/thumb/wwwww.png?1717557162",
    "width": "",
    "height": "",
    "ipfs_hash": ""
  },
  "support": { "email": "", "url": "" },
  "social": {
    "blog": "",
    "chat": "",
    "discord": "",
    "facebook": "",
    "forum": "",
    "github": "",
    "gitter": "",
    "instagram": "",
    "linkedin": "",
    "reddit": "",
    "slack": "",
    "telegram": "",
    "twitter": "",
    "youtube": ""
  }
}
